{
  "globals": {
    "EffectScope": true,
    "FileRequest": true,
    "FileRequestConfig": true,
    "HttpRequest": true,
    "HttpRequestConfig": true,
    "QQMapTobMap": true,
    "acceptHMRUpdate": true,
    "administrativeRegionList": true,
    "architectureAataListSearch": true,
    "arrayToOnly": true,
    "authToken": true,
    "authWeixin": true,
    "bMapToQQMap": true,
    "beforeAxiosEnter": true,
    "calendar": true,
    "chooseImage": true,
    "chooseLocation": true,
    "computed": true,
    "configRequestFunction": true,
    "createApp": true,
    "createPinia": true,
    "createRouter": true,
    "customRef": true,
    "dataEmpty": true,
    "defineAsyncComponent": true,
    "defineComponent": true,
    "defineStore": true,
    "effectScope": true,
    "enunList": true,
    "equipAlarmNotice": true,
    "equipSystemDataList": true,
    "equipmentDataAdd": true,
    "equipmentDataScan": true,
    "equipmentInstallAdd": true,
    "fillNumber": true,
    "findObjectValue": true,
    "fireControlKnowledgeDataPage": true,
    "getActivePinia": true,
    "getAppTheme": true,
    "getAppVersion": true,
    "getCurrentInstance": true,
    "getCurrentScope": true,
    "getDetails": true,
    "getDictList": true,
    "getElementStyle": true,
    "getLocation": true,
    "getName": true,
    "getPageLoad": true,
    "getPhoneNumber": true,
    "getProvider": true,
    "getSystemInfo": true,
    "getToken": true,
    "getUserInfo": true,
    "h": true,
    "httpErrorFunction": true,
    "httptResponseFunction": true,
    "inject": true,
    "installDataAllAdd": true,
    "installDataAllList": true,
    "isNull": true,
    "isObject": true,
    "isProxy": true,
    "isReactive": true,
    "isReadonly": true,
    "isRef": true,
    "jsonToGetData": true,
    "lesseeDataListAll": true,
    "lesseeEquipCount": true,
    "lesseeInstallEquipCount": true,
    "makePhoneCall": true,
    "mapActions": true,
    "mapGetters": true,
    "mapState": true,
    "mapStores": true,
    "mapWritableState": true,
    "markRaw": true,
    "maxnum": true,
    "messageSendPhone": true,
    "navigateBack": true,
    "navigateTo": true,
    "networkUnitDataListLessee": true,
    "nextTick": true,
    "onActivated": true,
    "onAddToFavorites": true,
    "onBackPress": true,
    "onBeforeMount": true,
    "onBeforeUnmount": true,
    "onBeforeUpdate": true,
    "onDeactivated": true,
    "onError": true,
    "onErrorCaptured": true,
    "onHide": true,
    "onLaunch": true,
    "onLoad": true,
    "onMounted": true,
    "onNavigationBarButtonTap": true,
    "onNavigationBarSearchInputChanged": true,
    "onNavigationBarSearchInputClicked": true,
    "onNavigationBarSearchInputConfirmed": true,
    "onNavigationBarSearchInputFocusChanged": true,
    "onPageNotFound": true,
    "onPageScroll": true,
    "onPullDownRefresh": true,
    "onReachBottom": true,
    "onReady": true,
    "onRenderTracked": true,
    "onRenderTriggered": true,
    "onResize": true,
    "onScopeDispose": true,
    "onServerPrefetch": true,
    "onShareAppMessage": true,
    "onShareTimeline": true,
    "onShow": true,
    "onTabItemTap": true,
    "onThemeChange": true,
    "onUnhandledRejection": true,
    "onUnload": true,
    "onUnmounted": true,
    "onUpdated": true,
    "openLocation": true,
    "path": true,
    "permission": true,
    "personUnit": true,
    "previewImage": true,
    "provide": true,
    "random": true,
    "randomText": true,
    "reLaunch": true,
    "reactive": true,
    "readonly": true,
    "redirectTo": true,
    "ref": true,
    "resetPinia": true,
    "resolveComponent": true,
    "resolveDirective": true,
    "roleSlideshowList": true,
    "routerTo": true,
    "scanCode": true,
    "setActivePinia": true,
    "setAppTheme": true,
    "setAppVersion": true,
    "setDetails": true,
    "setDictList": true,
    "setInitList": true,
    "setMapStoreSuffix": true,
    "setNavigationBarTitle": true,
    "setPageLoad": true,
    "setParamsJson": true,
    "setToken": true,
    "setUserInfo": true,
    "setyAxisMax": true,
    "shallowReactive": true,
    "shallowReadonly": true,
    "shallowRef": true,
    "showActionSheet": true,
    "showModal": true,
    "showToast": true,
    "storeToRefs": true,
    "stores": true,
    "switchTab": true,
    "sysUserDataInspector": true,
    "sysUserReset": true,
    "toRaw": true,
    "toRef": true,
    "toRefs": true,
    "triggerRef": true,
    "uniGetApp": true,
    "uniGetScene": true,
    "uniGetStorage": true,
    "uniSetApp": true,
    "uniSetStorage": true,
    "unilogin": true,
    "unref": true,
    "useAttrs": true,
    "useConfig": true,
    "useCssModule": true,
    "useCssVars": true,
    "useDetails": true,
    "useDictList": true,
    "useRoute": true,
    "useRouter": true,
    "useSlots": true,
    "useToken": true,
    "useUserInfo": true,
    "validation": true,
    "verifyData": true,
    "watch": true,
    "watchEffect": true,
    "watchPostEffect": true,
    "watchSyncEffect": true
  }
}